{
  "lastUpdated": "2026-03-18T16:10:02.124Z",
  "version": 151,
  "phi": 1.618033988749895,
  "resourcePatterns": [
    {
      "type": "RESOURCE_STABLE",
      "confidence": 1,
      "severity": "LOW",
      "firstSeen": "2026-03-18T03:35:01.395Z",
      "lastSeen": "2026-03-18T16:10:02.124Z",
      "occurrences": 151
    }
  ],
  "gitVelocity": "HIGH",
  "commitCount24h": 317,
  "topTopics": [
    {
      "word": "file(s)",
      "count": 257
    },
    {
      "word": "hcfp-auto",
      "count": 240
    },
    {
      "word": "changed",
      "count": 240
    },
    {
      "word": "auto-commit.log",
      "count": 199
    },
    {
      "word": "pattern_store.json",
      "count": 193
    },
    {
      "word": "resource-events.jsonl",
      "count": 73
    },
    {
      "word": "feat",
      "count": 36
    },
    {
      "word": "chore(auto)",
      "count": 17
    },
    {
      "word": "auto-commit",
      "count": 17
    },
    {
      "word": "stories.json",
      "count": 16
    }
  ]
}